setup.py
postcodeuk/__init__.py
postcodeuk.egg-info/PKG-INFO
postcodeuk.egg-info/SOURCES.txt
postcodeuk.egg-info/dependency_links.txt
postcodeuk.egg-info/requires.txt
postcodeuk.egg-info/top_level.txt
test/test_postcode.py