Metadata-Version: 1.0
Name: postcodeuk
Version: 0.4
Summary: library that supports validating and formatting post codes for UK
Home-page: UNKNOWN
Author: Lucas Santos
Author-email: lffsantos@gmail.com
License: UNKNOWN
Platform: UNKNOWN
